country_dialcode/__init__.py
country_dialcode/__init__.pyc
country_dialcode/admin.py
country_dialcode/apps.py
country_dialcode/compatibility.py
country_dialcode/forms.py
country_dialcode/intermediate_model_base_class.py
country_dialcode/models.py
country_dialcode/urls.py
country_dialcode/utils.py
country_dialcode/views.py
country_dialcode/__pycache__/__init__.cpython-35.pyc
country_dialcode/__pycache__/__init__.cpython-37.pyc
country_dialcode/fixtures/country_dialcode.json
country_dialcode/management/__init__.py
country_dialcode/management/commands/__init__.py
country_dialcode/management/commands/load_country_dialcode.py
country_dialcode/not_sql/country.sql
country_dialcode/not_sql/prefix.sql
country_dialcode/templatetags/__init__.py
country_dialcode/templatetags/country_dialcode_tags.py
country_dialcode/tests/__init__.py
country_dialcode/tests/runtests.py
country_dialcode/tests/test_settings.py
country_dialcode/tests/tests.py
country_dialcode/tests/utils.py
country_dialcode/utils/__init__.py
country_dialcode/utils/isoflag.py
django_country_dialcode_sb-0.6.4.dist-info/METADATA
django_country_dialcode_sb-0.6.4.dist-info/WHEEL
django_country_dialcode_sb-0.6.4.dist-info/top_level.txt
django_country_dialcode_sb-0.6.4.dist-info/RECORD
