Metadata-Version: 2.1
Name: django-country-dialcode-sb
Version: 0.6.4
Summary: Django Application providing Dialcode and Countries code
Home-page: http://github.com/Star2Billing/django-country-dialcode
Author: Belaid Arezqui
Author-email: areski@gmail.com
License: MIT License
Platform: UNKNOWN
Classifier: Development Status :: 5 - Production/Stable
Classifier: Environment :: Web Environment
Classifier: Framework :: Django
Classifier: Intended Audience :: Developers
Classifier: License :: OSI Approved :: MIT License
Classifier: Operating System :: OS Independent
Classifier: Programming Language :: Python
Classifier: Programming Language :: Python :: 2.7
Classifier: Programming Language :: Python :: 3
Classifier: Programming Language :: Python :: 3.5
Classifier: Topic :: Software Development :: Libraries :: Python Modules
